nozzle/__init__.py
nozzle/client.py
nozzle/exceptions.py
nozzle/steemd.py
nozzle/utils.py
steem_nozzle-0.2.0.dist-info/METADATA
steem_nozzle-0.2.0.dist-info/RECORD
steem_nozzle-0.2.0.dist-info/WHEEL
steem_nozzle-0.2.0.dist-info/top_level.txt
