Metadata-Version: 2.1
Name: steem-nozzle
Version: 0.2.0
Summary: A Python library for the Steem Blockchain
Home-page: https://github.com/blockbrothers/nozzle
Author: blockbrothers
Author-email: info@blockbrothers.io
License: MIT
Keywords: steem blockchain
Platform: UNKNOWN
Classifier: Development Status :: 3 - Alpha
Classifier: Intended Audience :: Developers
Classifier: License :: OSI Approved :: MIT License
Classifier: Programming Language :: Python :: 3 :: Only
Classifier: Programming Language :: Python :: 3.5
Classifier: Programming Language :: Python :: 3.6
Classifier: Topic :: Software Development
Classifier: Topic :: Software Development :: Libraries
Classifier: Topic :: Software Development :: Libraries :: Python Modules
Requires-Python: >=3.5
Requires-Dist: urllib3
Requires-Dist: certifi
